weather/__init__.py
weather/__main__.py
weather/server.py
weather_muxian-0.2.3.dist-info/METADATA
weather_muxian-0.2.3.dist-info/WHEEL
weather_muxian-0.2.3.dist-info/entry_points.txt
weather_muxian-0.2.3.dist-info/top_level.txt
weather_muxian-0.2.3.dist-info/RECORD
