Metadata-Version: 2.4
Name: weather-muxian
Version: 0.2.3
Summary: query weather
Requires-Python: >=3.11
Requires-Dist: httpx>=0.28.1
Requires-Dist: mcp[cli]>=1.6.0
Requires-Dist: openai>=1.69.0
